cpu/pipeline_simple_biss/register.v
// Author: L-C. Duca
// Date: 2015/11/20
// SPDX-License-Identifier: MIT


module register(clk, rst, next, out);
input clk, rst;
input [15:0] next;
output [15:0] out;
reg [15:0] out;

always @(posedge clk or posedge rst)
begin
	if(rst)
		out = 0;
	else
		out = next;
end

endmodule

cpu/pipeline_simple_biss/pipeline_biss.v
// Author: L-C. Duca
// Date: 2015/11/20
// SPDX-License-Identifier: MIT


module pipeline_biss_et1 (clk, rst, a, b);
input clk, rst;
input [15:0] a;
output [15:0] b;
wire  [15:0] b;
reg [15:0] next_b;

register r1(.clk(clk), .rst(rst), .next(next_b), .out(b));

always @(*)
	if(a != 0)
		next_b = a + 10;
	else
		next_b = 0;
endmodule
//-----------------------------------------------


module pipeline_biss_et2 (clk, rst, b, c);
input clk, rst;
input [15:0] b;
output [15:0] c;
wire  [15:0] c;
reg [15:0] next_c;

register r2(.clk(clk), .rst(rst), .next(next_c), .out(c));

always @(*)
	if(b != 0)
		next_c = b + 100;
	else
		next_c = 0;		
endmodule
//-----------------------------------------------


module pipeline_biss_et3 (clk, rst, c, d);
input clk, rst;
input [15:0] c;
output [15:0] d;
wire  [15:0] d;
reg [15:0] next_d;

register r3(.clk(clk), .rst(rst), .next(next_d), .out(d));

always @(*)
	if(c != 0)
		next_d = c + 1000;
	else
		next_d = 0;		
endmodule

cpu/pipeline_simple_biss/test_pipeline_biss.v
// Author: L-C. Duca
// Date: 2015/11/20
// SPDX-License-Identifier: MIT

`timescale 1ns/1ps

module test_pipeline_biss;
    reg clk;
    reg rst;
    reg [15:0] a;
    wire [15:0] b,c,d;

    parameter PERIOD = 100;

	pipeline_biss_et1 ps_et1 (.clk(clk), .rst(rst), .a(a), .b(b));
	pipeline_biss_et2 ps_et2 (.clk(clk), .rst(rst), .b(b), .c(c));
	pipeline_biss_et3 ps_et3 (.clk(clk), .rst(rst), .c(c), .d(d));

    initial begin  // Open the results file...
        $dumpfile("simple.vcd");
        $dumpvars(0, test_pipeline_biss);
        #2000 // Final time
        $finish;
	end
	
	// Data stimulus
    initial begin
	clk = 1'b0;
	a = 0;
        rst = 1'b1;        #(2*PERIOD);
        rst = 1'b0;        #PERIOD;
		
        a = 1;        #PERIOD;
        a = 2;        #PERIOD;
        a = 3;        #PERIOD;
        a = 4;        #PERIOD;
        a = 5;        #PERIOD;
        a = 6;        #PERIOD;		
        a = 0;        #PERIOD;
    end

    // Clock process for clk
    always #(PERIOD*0.5) clk = ~clk;

endmodule

cpu/pipeline_simple_biss/simple.vcd
$date
	Sat Mar 28 12:10:40 2020
$end
$version
	Icarus Verilog
$end
$timescale
	1ps
$end
$scope module test_pipeline_biss $end
$var wire 16 ! d [15:0] $end
$var wire 16 " c [15:0] $end
$var wire 16 # b [15:0] $end
$var reg 16 $ a [15:0] $end
$var reg 1 % clk $end
$var reg 1 & rst $end
$scope module ps_et1 $end
$var wire 16 ' a [15:0] $end
$var wire 1 % clk $end
$var wire 1 & rst $end
$var wire 16 ( b [15:0] $end
$var reg 16 ) next_b [15:0] $end
$scope module r1 $end
$var wire 1 % clk $end
$var wire 16 * next [15:0] $end
$var wire 1 & rst $end
$var reg 16 + out [15:0] $end
$upscope $end
$upscope $end
$scope module ps_et2 $end
$var wire 16 , b [15:0] $end
$var wire 1 % clk $end
$var wire 1 & rst $end
$var wire 16 - c [15:0] $end
$var reg 16 . next_c [15:0] $end
$scope module r2 $end
$var wire 1 % clk $end
$var wire 16 / next [15:0] $end
$var wire 1 & rst $end
$var reg 16 0 out [15:0] $end
$upscope $end
$upscope $end
$scope module ps_et3 $end
$var wire 16 1 c [15:0] $end
$var wire 1 % clk $end
$var wire 1 & rst $end
$var wire 16 2 d [15:0] $end
$var reg 16 3 next_d [15:0] $end
$scope module r3 $end
$var wire 1 % clk $end
$var wire 16 4 next [15:0] $end
$var wire 1 & rst $end
$var reg 16 5 out [15:0] $end
$upscope $end
$upscope $end
$upscope $end
$enddefinitions $end
#0
$dumpvars
b0 5
b0 4
b0 3
b0 2
b0 1
b0 0
b0 /
b0 .
b0 -
b0 ,
b0 +
b0 *
b0 )
b0 (
b0 '
1&
0%
b0 $
b0 #
b0 "
b0 !
$end
#50000
1%
#100000
0%
#150000
1%
#200000
0%
0&
#250000
1%
#300000
b1011 )
b1011 *
0%
b1 $
b1 '
#350000
b1101111 .
b1101111 /
b1011 #
b1011 (
b1011 +
b1011 ,
1%
#400000
b1100 )
b1100 *
0%
b10 $
b10 '
#450000
b10001010111 3
b10001010111 4
b1110000 .
b1110000 /
b1101111 "
b1101111 -
b1101111 0
b1101111 1
b1100 #
b1100 (
b1100 +
b1100 ,
1%
#500000
b1101 )
b1101 *
0%
b11 $
b11 '
#550000
b1110001 .
b1110001 /
b10001011000 3
b10001011000 4
b1101 #
b1101 (
b1101 +
b1101 ,
b1110000 "
b1110000 -
b1110000 0
b1110000 1
b10001010111 !
b10001010111 2
b10001010111 5
1%
#600000
b1110 )
b1110 *
0%
b100 $
b100 '
#650000
b10001011001 3
b10001011001 4
b1110010 .
b1110010 /
b10001011000 !
b10001011000 2
b10001011000 5
b1110001 "
b1110001 -
b1110001 0
b1110001 1
b1110 #
b1110 (
b1110 +
b1110 ,
1%
#700000
b1111 )
b1111 *
0%
b101 $
b101 '
#750000
b1110011 .
b1110011 /
b10001011010 3
b10001011010 4
b1111 #
b1111 (
b1111 +
b1111 ,
b1110010 "
b1110010 -
b1110010 0
b1110010 1
b10001011001 !
b10001011001 2
b10001011001 5
1%
#800000
b10000 )
b10000 *
0%
b110 $
b110 '
#850000
b10001011011 3
b10001011011 4
b1110100 .
b1110100 /
b10001011010 !
b10001011010 2
b10001011010 5
b1110011 "
b1110011 -
b1110011 0
b1110011 1
b10000 #
b10000 (
b10000 +
b10000 ,
1%
#900000
b0 )
b0 *
0%
b0 $
b0 '
#950000
b0 .
b0 /
b10001011100 3
b10001011100 4
b0 #
b0 (
b0 +
b0 ,
b1110100 "
b1110100 -
b1110100 0
b1110100 1
b10001011011 !
b10001011011 2
b10001011011 5
1%
#1000000
0%
#1050000
b0 3
b0 4
b10001011100 !
b10001011100 2
b10001011100 5
b0 "
b0 -
b0 0
b0 1
1%
#1100000
0%
#1150000
b0 !
b0 2
b0 5
1%
