wishbone/wb_def.v
// SPDX-License-Identifier: GPL-2.0
// Copyright (C) 2020, L-C. Duca

`ifndef WB_DEF_V
`define WB_DEF_V

`define dw    32
`define aw    32
`define selw  4
`define ms    2
`define ss    2
`define gntw  2

`define mbusw 77
`define sbusw 35

`endif

wishbone/wb_arb.v
// Modifications by Laurentiu-Cristian Duca
// laurentiu [dot] duca [at] gmail [dot] com

/////////////////////////////////////////////////////////////////////
////                                                             ////
//// Wishbone Creator                                            ////
//// Copyright (C) 2004 Daniel Wiklund, Linköping University     ////
////                                                             ////
//// This source file may be used and distributed without        ////
//// restriction provided that this copyright statement is not   ////
//// removed from the file and that any derivative work contains ////
//// the original copyright notice and the associated disclaimer.////
////                                                             ////
////     THIS SOFTWARE IS PROVIDED ``AS IS'' AND WITHOUT ANY     ////
//// EXPRESS OR IMPLIED WARRANTIES, INCLUDING, BUT NOT LIMITED   ////
//// TO, THE IMPLIED WARRANTIES OF MERCHANTABILITY AND FITNESS   ////
//// FOR A PARTICULAR PURPOSE. IN NO EVENT SHALL THE AUTHOR      ////
//// OR CONTRIBUTORS BE LIABLE FOR ANY DIRECT, INDIRECT,         ////
//// INCIDENTAL, SPECIAL, EXEMPLARY, OR CONSEQUENTIAL DAMAGES    ////
//// (INCLUDING, BUT NOT LIMITED TO, PROCUREMENT OF SUBSTITUTE   ////
//// GOODS OR SERVICES; LOSS OF USE, DATA, OR PROFITS; OR        ////
//// BUSINESS INTERRUPTION) HOWEVER CAUSED AND ON ANY THEORY OF  ////
//// LIABILITY, WHETHER IN  CONTRACT, STRICT LIABILITY, OR TORT  ////
//// (INCLUDING NEGLIGENCE OR OTHERWISE) ARISING IN ANY WAY OUT  ////
//// OF THE USE OF THIS SOFTWARE, EVEN IF ADVISED OF THE         ////
//// POSSIBILITY OF SUCH DAMAGE.                                 ////
////                                                             ////
/////////////////////////////////////////////////////////////////////

`include "wb_def.v"

module wb_arb(clk_i, rst_i, req_i, gnt_o);

input            clk_i;
input            rst_i;
input  [`ms-1:0] req_i;
output [`ms-1:0] gnt_o;

parameter [`gntw-1:0] grant0 = 3'h0,
                      grant1 = 3'h1;

reg [`gntw-1:0] state, next_state;

always @ (posedge clk_i)
  if (rst_i) state <= #1 grant0;
  else       state <= #1 next_state;

assign gnt_o[0] = (state == 3'h0);
assign gnt_o[1] = (state == 3'h1);

always @ (state or req_i) begin
  case(state)
    grant0:
      if (req_i[0]) next_state = grant0;
		else if (req_i[1]) next_state = grant1;
		else next_state = grant0;
    grant1:
      if (req_i[1]) next_state = grant1;
		else if (req_i[0]) next_state = grant0;
        else next_state = grant1;
  endcase
end

endmodule

wishbone/wb_top.v
// Modifications by Laurentiu-Cristian Duca
// laurentiu [dot] duca [at] gmail [dot] com
// 2020/03/24

/////////////////////////////////////////////////////////////////////
////                                                             ////
//// Wishbone Creator                                            ////
//// Copyright (C) 2004 Daniel Wiklund, Linköping University     ////
////                                                             ////
//// This source file may be used and distributed without        ////
//// restriction provided that this copyright statement is not   ////
//// removed from the file and that any derivative work contains ////
//// the original copyright notice and the associated disclaimer.////
////                                                             ////
////     THIS SOFTWARE IS PROVIDED ``AS IS'' AND WITHOUT ANY     ////
//// EXPRESS OR IMPLIED WARRANTIES, INCLUDING, BUT NOT LIMITED   ////
//// TO, THE IMPLIED WARRANTIES OF MERCHANTABILITY AND FITNESS   ////
//// FOR A PARTICULAR PURPOSE. IN NO EVENT SHALL THE AUTHOR      ////
//// OR CONTRIBUTORS BE LIABLE FOR ANY DIRECT, INDIRECT,         ////
//// INCIDENTAL, SPECIAL, EXEMPLARY, OR CONSEQUENTIAL DAMAGES    ////
//// (INCLUDING, BUT NOT LIMITED TO, PROCUREMENT OF SUBSTITUTE   ////
//// GOODS OR SERVICES; LOSS OF USE, DATA, OR PROFITS; OR        ////
//// BUSINESS INTERRUPTION) HOWEVER CAUSED AND ON ANY THEORY OF  ////
//// LIABILITY, WHETHER IN  CONTRACT, STRICT LIABILITY, OR TORT  ////
//// (INCLUDING NEGLIGENCE OR OTHERWISE) ARISING IN ANY WAY OUT  ////
//// OF THE USE OF THIS SOFTWARE, EVEN IF ADVISED OF THE         ////
//// POSSIBILITY OF SUCH DAMAGE.                                 ////
////                                                             ////
/////////////////////////////////////////////////////////////////////

`include "wb_def.v"

module wb_top(
  clk_i, rst_i,

  // Master 0 Interface
  m0_dat_i, m0_dat_o, m0_adr_i, m0_sel_i,
  m0_we_i,  m0_cyc_i, m0_stb_i, m0_cab_i,
  m0_ack_o, m0_err_o, m0_rty_o, m0_cti_i,
  m0_bte_i,

  // Master 1 Interface
  m1_dat_i, m1_dat_o, m1_adr_i, m1_sel_i,
  m1_we_i,  m1_cyc_i, m1_stb_i, m1_cab_i,
  m1_ack_o, m1_err_o, m1_rty_o, m1_cti_i,
  m1_bte_i,

  // Slave 0 Interface
  s0_dat_o, s0_dat_i, s0_adr_o, s0_sel_o,
  s0_we_o,  s0_cyc_o, s0_stb_o, s0_cab_o,
  s0_ack_i, s0_err_i, s0_rty_i, s0_cti_o,
  s0_bte_o,

  // Slave 1 Interface
  s1_dat_o, s1_dat_i, s1_adr_o, s1_sel_o,
  s1_we_o,  s1_cyc_o, s1_stb_o, s1_cab_o,
  s1_ack_i, s1_err_i, s1_rty_i, s1_cti_o,
  s1_bte_o,

  // Test/debug output
  grant_o
  );

parameter s0_addr_width = 8;
parameter s0_addr = 8'h40;
parameter s1_addr_width = 8;
parameter s1_addr = 8'h90;

// Syscon interface
input            clk_i, rst_i;
output [`ms-1:0] grant_o;

// Master 0 Interface
input  [`dw-1:0]    m0_dat_i;
output [`dw-1:0]    m0_dat_o;
input  [`aw-1:0]    m0_adr_i;
input  [`selw-1:0]  m0_sel_i;
input               m0_we_i;
input               m0_cyc_i;
input               m0_stb_i;
input               m0_cab_i;
output              m0_ack_o;
output              m0_rty_o;
output              m0_err_o;
input  [2:0]        m0_cti_i;
input  [1:0]        m0_bte_i;

// Master 1 Interface
input  [`dw-1:0]    m1_dat_i;
output [`dw-1:0]    m1_dat_o;
input  [`aw-1:0]    m1_adr_i;
input  [`selw-1:0]  m1_sel_i;
input               m1_we_i;
input               m1_cyc_i;
input               m1_stb_i;
input               m1_cab_i;
output              m1_ack_o;
output              m1_rty_o;
output              m1_err_o;
input  [2:0]        m1_cti_i;
input  [1:0]        m1_bte_i;

// Slave 0 Interface
output [`dw-1:0]    s0_dat_o;
input  [`dw-1:0]    s0_dat_i;
output [`aw-1:0]    s0_adr_o;
output [`selw-1:0]  s0_sel_o;
output              s0_we_o;
output              s0_cyc_o;
output              s0_stb_o;
output              s0_cab_o;
input               s0_ack_i;
input               s0_rty_i;
input               s0_err_i;
output [2:0]        s0_cti_o;
output [1:0]        s0_bte_o;

// Slave 1 Interface
output [`dw-1:0]    s1_dat_o;
input  [`dw-1:0]    s1_dat_i;
output [`aw-1:0]    s1_adr_o;
output [`selw-1:0]  s1_sel_o;
output              s1_we_o;
output              s1_cyc_o;
output              s1_stb_o;
output              s1_cab_o;
input               s1_ack_i;
input               s1_rty_i;
input               s1_err_i;
output [2:0]        s1_cti_o;
output [1:0]        s1_bte_o;

// Master and slave input/output signals for mux bus
wire [`ms-1:0]    gnt;
wire [`ss-1:0]    ssel;
wire [`ss-1:0]    m0_ssel;
wire [`ss-1:0]    m1_ssel;
wire [`sbusw-1:0] s_signal;
wire [`mbusw-1:0] m_signal;
// Master 0 inputs
wire [`mbusw-1:0] m0_signal;
assign m0_signal = {m0_adr_i, m0_dat_i, m0_sel_i, m0_we_i, m0_cyc_i, m0_stb_i, m0_cab_i, m0_cti_i, m0_bte_i};
// Master 0 outputs
assign m0_dat_o = s_signal[34:3];
assign m0_ack_o = s_signal[2] & gnt[0];
assign m0_err_o = s_signal[1] & gnt[0];
assign m0_rty_o = s_signal[0] & gnt[0];

// Master 1 inputs
wire [`mbusw-1:0] m1_signal;
assign m1_signal = {m1_adr_i, m1_dat_i, m1_sel_i, m1_we_i, m1_cyc_i, m1_stb_i, m1_cab_i, m1_cti_i, m1_bte_i};
// Master 1 outputs
assign m1_dat_o = s_signal[34:3];
assign m1_ack_o = s_signal[2] & gnt[1];
assign m1_err_o = s_signal[1] & gnt[1];
assign m1_rty_o = s_signal[0] & gnt[1];

// Slave 0 inputs
wire [`sbusw-1:0] s0_signal;
assign s0_signal = {s0_dat_i, s0_ack_i, s0_err_i, s0_rty_i};
// Slave 0 outputs
assign s0_adr_o = m_signal[76:45];
assign s0_dat_o = m_signal[44:13];
assign s0_sel_o = m_signal[12:9];
assign s0_we_o  = m_signal[8];
assign s0_cyc_o = m_signal[7];
assign s0_stb_o = m_signal[6] & m_signal[7] & ssel[0];
assign s0_cab_o = m_signal[5];
assign s0_cti_o = m_signal[4:2];
assign s0_bte_o = m_signal[1:0];

// Slave 1 inputs
wire [`sbusw-1:0] s1_signal;
assign s1_signal = {s1_dat_i, s1_ack_i, s1_err_i, s1_rty_i};
// Slave 1 outputs
assign s1_adr_o = m_signal[76:45];
assign s1_dat_o = m_signal[44:13];
assign s1_sel_o = m_signal[12:9];
assign s1_we_o  = m_signal[8];
assign s1_cyc_o = m_signal[7];
assign s1_stb_o = m_signal[6] & m_signal[7] & ssel[1];
assign s1_cab_o = m_signal[5];
assign s1_cti_o = m_signal[4:2];
assign s1_bte_o = m_signal[1:0];

assign m_signal = gnt[0] ? m0_signal :
				  m1_signal;

assign s_signal = ssel[0] ? s0_signal :
				  ssel[1] ?	s1_signal : s0_signal;

assign ssel     = gnt[0] ? m0_ssel :
				  gnt[1] ? m1_ssel : 10'b0;

assign m0_ssel[0] = (m0_adr_i[s0_addr_width-1:0] == s0_addr);
assign m0_ssel[1] = (m0_adr_i[s1_addr_width-1:0] == s1_addr);
assign m1_ssel[0] = (m1_adr_i[s0_addr_width-1:0] == s0_addr);
assign m1_ssel[1] = (m1_adr_i[s1_addr_width-1:0] == s1_addr);

wb_arb arb(
  .clk_i(clk_i),
  .rst_i(rst_i),
  .req_i({m1_cyc_i, m0_cyc_i}),
  .gnt_o(gnt)
);

assign grant_o = gnt;

endmodule

wishbone/wb_slave.v
// SPDX-License-Identifier: GPL-2.0
// Copyright (C) 2020, L-C. Duca

`timescale 1ns/1ps
`include "wb_def.v"
  
module wb_slave	(input clk_i, rst_i, slave_we_i, slave_stb_i, slave_cyc_i,
				 input[`dw-1:0] slave_dat_i, output reg slave_ack_o, output reg [`dw-1:0] slave_dat_o);

   parameter slave_param = `dw'd0;
   
   always @(posedge clk_i or posedge rst_i)
	begin
		if(rst_i) begin
			slave_ack_o = 0;
			slave_dat_o = 0;
		end else begin
			slave_ack_o = slave_stb_i && slave_cyc_i;
			if (slave_cyc_i && slave_stb_i && slave_we_i)
			begin
				slave_dat_o = slave_param;
				$display("slave_slave_1: time=%dns slave_dat_i=%h\n", $time, slave_dat_i);
			end
		end
   end

      
endmodule

wishbone/wb_master.v
// SPDX-License-Identifier: GPL-2.0
// Copyright (C) 2020, L-C. Duca

`timescale 1ns/1ps
`include "wb_def.v"

module wb_master (input clk_i, input rst_i,
					output reg m_cyc_o, output reg m_stb_o, output reg m_we_o,
				  output reg [`aw-1:0] m_addr_o,
					input m_ack_i,
					output reg [`selw-1:0] m_sel_o,
				  output reg [`dw-1:0] m_data_o,
				  input [`dw-1:0] m_data_i);
	
   	parameter master_param = `dw'd0;
		parameter slave_address = `aw'd0;
	reg transfer_done;
	
	always @(posedge clk_i or posedge rst_i)
	begin
		if(rst_i) begin
			transfer_done = 0;
			m_cyc_o = 0; m_stb_o = 0; m_we_o = 0;
			m_sel_o = {`selw{1'b1}};
			m_data_o = 0;
			m_addr_o = 0;
		end else if(!transfer_done) begin
			if(m_ack_i) begin
				transfer_done = 1;
				$display("wb_master: time=%dns m_data_i=%h\n", $time, m_data_i);
				m_cyc_o = 0; m_stb_o = 0; m_we_o = 0;
			end
			else begin
				m_cyc_o = 1; m_stb_o = 1; m_we_o = 1;
				// select all bytes
				m_sel_o = {`selw{1'b1}};
				m_data_o = master_param;
				m_addr_o = slave_address;
			end	
		end
   end

endmodule

wishbone/top.v
// SPDX-License-Identifier: GPL-2.0
// Copyright (C) 2020, L-C. Duca

`timescale 1ns/1ps
`include "wb_def.v"

module top;

reg clk_i, rst_i;
	
always #50 clk_i = ~clk_i;
	
initial begin
	$dumpfile("wb.vcd");
	$dumpvars(0, top);
	clk_i = 0;
	rst_i = 1;
	#250;
	rst_i = 0;
	#2000;
	$finish;
end
   
   // master 0 <-> WISHBONE
   wire [`dw-1:0] 	m0_dat_i;	// input data bus
   wire			m0_cyc, m0_stb, m0_we;
   wire [`aw-1:0] 	m0_adr;	// address bus outputs
   wire [`selw-1:0] 		m0_sel;	// byte select outputs
   wire [`dw-1:0] 	m0_dat_o;	// output data bus
   wire			m0_ack, m0_err, m0_rty, m0_cab;
   wire [2:0] 		m0_cti;	// cycle type identifier
   wire [1:0] 		m0_bte;	// burst type extension

   // master1 <-> WISHBONE
   wire [`dw-1:0] 	m1_dat_i;	// input data bus
   wire			m1_cyc, m1_stb, m1_we;
   wire [`aw-1:0] 	m1_adr;	// address bus outputs
   wire [`selw-1:0] 		m1_sel;	// byte select outputs
   wire [`dw-1:0] 	m1_dat_o;	// output data bus
   wire			m1_ack, m1_err, m1_rty, m1_cab;
   wire [2:0] 		m1_cti;	// cycle type identifier
   wire [1:0] 		m1_bte;	// burst type extension

   // WISHBONE <=> I/O slave 0
   wire [`aw-1:0] 	s0_addr;	// address bus
   wire [`dw-1:0] 	s0_dat_i;	// input data bus
   wire [`dw-1:0] 	s0_dat_o;	// output data bus
   wire 		s0_ack, s0_cyc, s0_stb, s0_we;
   wire [3:0] 		s0_sel;
   
   // WISHBONE <=> I/O slave 1
   wire [`aw-1:0] 	s1_addr;
   wire [`dw-1:0] 	s1_dat_i;
   wire [`dw-1:0] 	s1_dat_o;
   wire 		s1_we, s1_cyc, s1_stb, s1_ack;

	// Instantiate masters
	wb_master #(`dw'h20, `aw'h40) master0 (
      .clk_i(clk_i), .rst_i(rst_i),
	  .m_cyc_o(m0_cyc), .m_stb_o(m0_stb), .m_we_o(m0_we), 
	  .m_addr_o(m0_adr), .m_ack_i(m0_ack), 
      .m_sel_o(m0_sel), .m_data_o(m0_dat_o), .m_data_i(m0_dat_i)
     );
	wb_master #(`dw'h30, `aw'h90) master1 (
      .clk_i(clk_i), .rst_i(rst_i),
	  .m_cyc_o(m1_cyc), .m_stb_o(m1_stb), .m_we_o(m1_we), 
	  .m_addr_o(m1_adr), .m_ack_i(m1_ack), 
	  .m_sel_o(m1_sel), .m_data_o(m1_dat_o), .m_data_i(m1_dat_i)
     );
     
    // Instantiate slaves
	wb_slave #(`dw'h25) slave0 (
	  .clk_i(clk_i), .rst_i(rst_i), 
	  .slave_we_i(s0_we), .slave_stb_i(s0_stb), .slave_cyc_i(s0_cyc), 
      .slave_dat_i(s0_dat_o), .slave_dat_o(s0_dat_i), 
      .slave_ack_o(s0_ack));
	wb_slave #(`dw'h35) slave1 (
	  .clk_i(clk_i), .rst_i(rst_i), 
      .slave_we_i(s1_we), .slave_stb_i(s1_stb), .slave_cyc_i(s1_cyc), 
      .slave_dat_i(s1_dat_o), .slave_dat_o(s1_dat_i), 
      .slave_ack_o(s1_ack));
   
    // Instantiate wishbone bus
	wb_top #(8, 8'h40, 8, 8'h90) wb_bus ( 
	   .clk_i(clk_i), .rst_i(rst_i),
	   // Master 0 Interface
	   .m0_dat_i(m0_dat_o), .m0_dat_o(m0_dat_i),
	   .m0_adr_i(m0_adr), .m0_sel_i(m0_sel),
	   .m0_we_i(m0_we), .m0_cyc_i(m0_cyc), .m0_stb_i(m0_stb),
	   .m0_cab_i(m0_cab), .m0_ack_o(m0_ack), .m0_err_o(m0_err), .m0_rty_o(m0_rty), .m0_cti_i(m0_cti), .m0_bte_i(m0_bte),
	   // Master 1 Interface
	   .m1_dat_i(m1_dat_o), .m1_dat_o(m1_dat_i),
	   .m1_adr_i(m1_adr), .m1_sel_i(m1_sel),
	   .m1_we_i(m1_we), .m1_cyc_i(m1_cyc), .m1_stb_i(m1_stb),
	   .m1_cab_i(m1_cab), .m1_ack_o(m1_ack), .m1_err_o(m1_err), .m1_rty_o(m1_rty), .m1_cti_i(m1_cti), .m1_bte_i(m1_bte),
	   // Slave 0 Interface
	   .s0_dat_o(s0_dat_o), .s0_dat_i(s0_dat_i), 				
	   .s0_adr_o(s0_addr), .s0_sel_o(s0_sel),
	   .s0_we_o(s0_we), .s0_cyc_o(s0_cyc), .s0_stb_o(s0_stb),
	   .s0_cab_o(), .s0_ack_i(s0_ack), .s0_err_i(1'b0), .s0_rty_i(1'b0), .s0_cti_o(), .s0_bte_o(),
	   // Slave 1 Interface
	   .s1_dat_o(s1_dat_o), .s1_dat_i(s1_dat_i), 				
	   .s1_adr_o(s1_addr), .s1_sel_o(),
	   .s1_we_o(s1_we), .s1_cyc_o(s1_cyc), .s1_stb_o(s1_stb),
	   .s1_cab_o(), .s1_ack_i(s1_ack), .s1_err_i(1'b0), .s1_rty_i(1'b0), .s1_cti_o(), .s1_bte_o(),
	   .grant_o());

endmodule

wishbone/wb.vcd
$date
	Fri Mar 27 11:10:58 2020
$end
$version
	Icarus Verilog
$end
$timescale
	1ps
$end
$scope module top $end
$var wire 2 ! m0_bte [1:0] $end
$var wire 1 " m0_cab $end
$var wire 3 # m0_cti [2:0] $end
$var wire 2 $ m1_bte [1:0] $end
$var wire 1 % m1_cab $end
$var wire 3 & m1_cti [2:0] $end
$var wire 1 ' s1_we $end
$var wire 1 ( s1_stb $end
$var wire 32 ) s1_dat_o [31:0] $end
$var wire 32 * s1_dat_i [31:0] $end
$var wire 1 + s1_cyc $end
$var wire 32 , s1_addr [31:0] $end
$var wire 1 - s1_ack $end
$var wire 1 . s0_we $end
$var wire 1 / s0_stb $end
$var wire 4 0 s0_sel [3:0] $end
$var wire 32 1 s0_dat_o [31:0] $end
$var wire 32 2 s0_dat_i [31:0] $end
$var wire 1 3 s0_cyc $end
$var wire 32 4 s0_addr [31:0] $end
$var wire 1 5 s0_ack $end
$var wire 1 6 m1_we $end
$var wire 1 7 m1_stb $end
$var wire 4 8 m1_sel [3:0] $end
$var wire 1 9 m1_rty $end
$var wire 1 : m1_err $end
$var wire 32 ; m1_dat_o [31:0] $end
$var wire 32 < m1_dat_i [31:0] $end
$var wire 1 = m1_cyc $end
$var wire 32 > m1_adr [31:0] $end
$var wire 1 ? m1_ack $end
$var wire 1 @ m0_we $end
$var wire 1 A m0_stb $end
$var wire 4 B m0_sel [3:0] $end
$var wire 1 C m0_rty $end
$var wire 1 D m0_err $end
$var wire 32 E m0_dat_o [31:0] $end
$var wire 32 F m0_dat_i [31:0] $end
$var wire 1 G m0_cyc $end
$var wire 32 H m0_adr [31:0] $end
$var wire 1 I m0_ack $end
$var reg 1 J clk_i $end
$var reg 1 K rst_i $end
$scope module master0 $end
$var wire 1 J clk_i $end
$var wire 1 K rst_i $end
$var wire 32 L m_data_i [31:0] $end
$var wire 1 I m_ack_i $end
$var reg 32 M m_addr_o [31:0] $end
$var reg 1 G m_cyc_o $end
$var reg 32 N m_data_o [31:0] $end
$var reg 4 O m_sel_o [3:0] $end
$var reg 1 A m_stb_o $end
$var reg 1 @ m_we_o $end
$var reg 1 P transfer_done $end
$upscope $end
$scope module master1 $end
$var wire 1 J clk_i $end
$var wire 1 K rst_i $end
$var wire 32 Q m_data_i [31:0] $end
$var wire 1 ? m_ack_i $end
$var reg 32 R m_addr_o [31:0] $end
$var reg 1 = m_cyc_o $end
$var reg 32 S m_data_o [31:0] $end
$var reg 4 T m_sel_o [3:0] $end
$var reg 1 7 m_stb_o $end
$var reg 1 6 m_we_o $end
$var reg 1 U transfer_done $end
$upscope $end
$scope module slave0 $end
$var wire 1 J clk_i $end
$var wire 1 K rst_i $end
$var wire 1 . slave_we_i $end
$var wire 1 / slave_stb_i $end
$var wire 32 V slave_dat_i [31:0] $end
$var wire 1 3 slave_cyc_i $end
$var reg 1 5 slave_ack_o $end
$var reg 32 W slave_dat_o [31:0] $end
$upscope $end
$scope module slave1 $end
$var wire 1 J clk_i $end
$var wire 1 K rst_i $end
$var wire 1 ' slave_we_i $end
$var wire 1 ( slave_stb_i $end
$var wire 32 X slave_dat_i [31:0] $end
$var wire 1 + slave_cyc_i $end
$var reg 1 - slave_ack_o $end
$var reg 32 Y slave_dat_o [31:0] $end
$upscope $end
$scope module wb_bus $end
$var wire 1 J clk_i $end
$var wire 2 Z grant_o [1:0] $end
$var wire 1 I m0_ack_o $end
$var wire 32 [ m0_adr_i [31:0] $end
$var wire 2 \ m0_bte_i [1:0] $end
$var wire 1 " m0_cab_i $end
$var wire 3 ] m0_cti_i [2:0] $end
$var wire 1 G m0_cyc_i $end
$var wire 32 ^ m0_dat_i [31:0] $end
$var wire 1 D m0_err_o $end
$var wire 1 C m0_rty_o $end
$var wire 4 _ m0_sel_i [3:0] $end
$var wire 1 A m0_stb_i $end
$var wire 1 @ m0_we_i $end
$var wire 1 ? m1_ack_o $end
$var wire 32 ` m1_adr_i [31:0] $end
$var wire 2 a m1_bte_i [1:0] $end
$var wire 1 % m1_cab_i $end
$var wire 3 b m1_cti_i [2:0] $end
$var wire 1 = m1_cyc_i $end
$var wire 32 c m1_dat_i [31:0] $end
$var wire 1 : m1_err_o $end
$var wire 1 9 m1_rty_o $end
$var wire 4 d m1_sel_i [3:0] $end
$var wire 1 7 m1_stb_i $end
$var wire 1 6 m1_we_i $end
$var wire 1 K rst_i $end
$var wire 1 5 s0_ack_i $end
$var wire 32 e s0_dat_i [31:0] $end
$var wire 1 f s0_err_i $end
$var wire 1 g s0_rty_i $end
$var wire 1 / s0_stb_o $end
$var wire 1 - s1_ack_i $end
$var wire 32 h s1_dat_i [31:0] $end
$var wire 1 i s1_err_i $end
$var wire 1 j s1_rty_i $end
$var wire 1 ( s1_stb_o $end
$var wire 2 k ssel [1:0] $end
$var wire 35 l s_signal [34:0] $end
$var wire 1 ' s1_we_o $end
$var wire 35 m s1_signal [34:0] $end
$var wire 4 n s1_sel_o [3:0] $end
$var wire 32 o s1_dat_o [31:0] $end
$var wire 1 + s1_cyc_o $end
$var wire 3 p s1_cti_o [2:0] $end
$var wire 1 q s1_cab_o $end
$var wire 2 r s1_bte_o [1:0] $end
$var wire 32 s s1_adr_o [31:0] $end
$var wire 1 . s0_we_o $end
$var wire 35 t s0_signal [34:0] $end
$var wire 4 u s0_sel_o [3:0] $end
$var wire 32 v s0_dat_o [31:0] $end
$var wire 1 3 s0_cyc_o $end
$var wire 3 w s0_cti_o [2:0] $end
$var wire 1 x s0_cab_o $end
$var wire 2 y s0_bte_o [1:0] $end
$var wire 32 z s0_adr_o [31:0] $end
$var wire 77 { m_signal [76:0] $end
$var wire 2 | m1_ssel [1:0] $end
$var wire 77 } m1_signal [76:0] $end
$var wire 32 ~ m1_dat_o [31:0] $end
$var wire 2 !" m0_ssel [1:0] $end
$var wire 77 "" m0_signal [76:0] $end
$var wire 32 #" m0_dat_o [31:0] $end
$var wire 2 $" gnt [1:0] $end
$scope module arb $end
$var wire 1 J clk_i $end
$var wire 2 %" req_i [1:0] $end
$var wire 1 K rst_i $end
$var wire 2 &" gnt_o [1:0] $end
$var reg 2 '" next_state [1:0] $end
$var reg 2 (" state [1:0] $end
$upscope $end
$upscope $end
$upscope $end
$enddefinitions $end
#0
$dumpvars
bx ("
bx '"
bx &"
b0 %"
bx $"
b0 #"
b1111000zzzzzz ""
b0 !"
b0 ~
b1111000zzzzzz }
b0 |
b1111000zzzzzz {
b0 z
bz y
zx
bz w
b0 v
b1111 u
b0 t
b0 s
bz r
zq
bz p
b0 o
b1111 n
b0 m
b0 l
b0 k
0j
0i
b0 h
0g
0f
b0 e
b1111 d
b0 c
bz b
bz a
b0 `
b1111 _
b0 ^
bz ]
bz \
b0 [
bx Z
b0 Y
b0 X
b0 W
b0 V
0U
b1111 T
b0 S
b0 R
b0 Q
0P
b1111 O
b0 N
b0 M
b0 L
1K
0J
0I
b0 H
0G
b0 F
b0 E
0D
0C
b1111 B
0A
0@
0?
b0 >
0=
b0 <
b0 ;
0:
09
b1111 8
07
06
05
b0 4
03
b0 2
b0 1
b1111 0
0/
0.
0-
b0 ,
0+
b0 *
b0 )
0(
0'
bz &
z%
bz $
bz #
z"
bz !
$end
#50000
1J
#51000
b0 '"
b1 Z
b1 $"
b1 &"
b0 ("
#100000
0J
#150000
1J
#200000
0J
#250000
1/
b1 k
1+
1'
b100000 )
b100000 X
b100000 o
b1000000 ,
b1000000 s
13
1.
b100000 1
b100000 V
b100000 v
b1000000 4
b1000000 z
b10 |
b1 !"
b1000000000000000000000000000000001000001111111zzzzzz {
b10010000 >
b10010000 R
b10010000 `
b110000 ;
b110000 S
b110000 c
16
17
b10010000000000000000000000000000001100001111111zzzzzz }
1=
b1000000 H
b1000000 M
b1000000 [
b100000 E
b100000 N
b100000 ^
1@
1A
b1000000000000000000000000000000001000001111111zzzzzz ""
b11 %"
1G
1J
0K
#300000
0J
#350000
1I
b100101 <
b100101 Q
b100101 ~
b100101 F
b100101 L
b100101 #"
b100101100 l
b100101 2
b100101 W
b100101 e
b100101100 t
15
1J
#400000
0J
#450000
0/
0+
0'
03
0.
b1000000000000000000000000000000001000001111000zzzzzz {
b1 '"
0@
0A
b1000000000000000000000000000000001000001111000zzzzzz ""
b10 %"
0G
1P
1J
#500000
0J
#550000
0I
b100101000 l
b100101000 t
05
1J
#551000
b0 <
b0 Q
b0 ~
b0 F
b0 L
b0 #"
b0 l
1(
b10 k
1+
1'
b110000 )
b110000 X
b110000 o
b10010000 ,
b10010000 s
13
1.
b110000 1
b110000 V
b110000 v
b10010000 4
b10010000 z
b10010000000000000000000000000000001100001111111zzzzzz {
b10 Z
b10 $"
b10 &"
b1 ("
#600000
0J
#650000
1?
b110101 <
b110101 Q
b110101 ~
b110101 F
b110101 L
b110101 #"
b110101100 l
b110101 *
b110101 Y
b110101 h
b110101100 m
1-
1J
#700000
0J
#750000
0(
0+
0'
03
0.
b10010000000000000000000000000000001100001111000zzzzzz {
06
07
b10010000000000000000000000000000001100001111000zzzzzz }
b0 %"
0=
1U
1J
#800000
0J
#850000
0?
b110101000 l
b110101000 m
0-
1J
