single_pulse/vhdl/single_pulse.vhd
-----------------------------------------------------
-- single pulse from a multi-periods-contiguous pulse
-- date: 20180820-1700
-- Copyright (C) 2018 Laurentiu-Cristian Duca
-- SPDX-License-Identifier: GPL-2.0
-----------------------------------------------------

library IEEE;
use IEEE.STD_LOGIC_1164.ALL;
use IEEE.NUMERIC_STD.ALL;
--use ieee.std_logic_arith.all;  
--use ieee.std_logic_unsigned.all;

-----------------------------------------------------

entity single_pulse is
port(	clk, rst_l: in std_logic;
		ub: in std_logic;
		ubsing: out std_logic
);
end single_pulse;

-----------------------------------------------------

architecture single_pulse_arch of single_pulse is

   signal next_state, state: std_logic;
	signal ubsing_reg, next_ubsing_reg: std_logic;

begin
	ubsing <= ubsing_reg;
  
   state_reg: process(clk, rst_l)
   begin
		if (rst_l='0') then
			state <= '0';
			ubsing_reg <= '0';
		elsif (rising_edge(clk)) then
				state <= next_state;
				ubsing_reg <= next_ubsing_reg;
		end if;
   end process;

   comb_logic: process(state, ub)
	begin
		next_state <= state;
		next_ubsing_reg <= '0';
		case state is
			when '0' =>
				if (ub = '1') then
					 next_state <= '1';
					 next_ubsing_reg <= '1';
				end if;
			when '1' =>	
				if (ub = '0') then
					next_state <= '0';
				end if;
			when others =>
				-- this is forced by the vhdl compiler
				--next_state <= '0';
				--next_ubsing_reg <= '0';
		end case;
   end process;

end single_pulse_arch;

-----------------------------------------------------

single_pulse/vhdl/single_pulse_tb.vhd
-----------------------------------------------------------------
-- Booth algorithm for multiplication
-- Copyright (C) 2020 Laurentiu Duca
-- SPDX-License-Identifier: GPL-2.0
-----------------------------------------------------------------

library	ieee;
--use ieee.std_logic_arith.all;  
--use ieee.std_logic_unsigned.all;
use ieee.std_logic_1164.all;

entity single_pulse_tb is			-- entity declaration
end single_pulse_tb;

-----------------------------------------------------------------

architecture TB of single_pulse_tb is

signal T_clk: std_logic; 
signal T_rst_l:	std_logic;
signal T_ub: std_logic;
signal T_ubsing: std_logic;
signal stop_simulation: std_logic := '0';

component single_pulse
port(	clk:		in std_logic;
		rst_l:		in std_logic;
		ub:			in std_logic;
		ubsing:		out std_logic
);
end component;

begin
	
    U_single_pulse: single_pulse port map(rst_l=>T_rst_l, clk=>T_clk, ub=>T_ub, ubsing=>T_ubsing);
	
    process
    begin
		if stop_simulation = '0' then
			T_clk <= '1';			-- clock cycle 10 ns
			wait for 5 ns;
			T_clk <= '0';
			wait for 5 ns;
		else
			wait;
		end if;
	end process;
	
    process			   
    begin
	T_rst_l <= '0';
	T_ub <= '0';
	wait for 20 ns;
	T_rst_l	<= '1';								 
	wait for 30 ns;
	T_ub <= '1';
	wait for 50 ns;		
	T_ub <= '0';
	wait for 50 ns;

	-- stop simulation.
	--assert false report "end of simulation" severity failure;
	stop_simulation <= '1';
	wait;

    end process;	 
	
end TB;

----------------------------------------------------------------------
configuration CFG_TB of single_pulse_tb is
	for TB
	end for;
end CFG_TB;
-----------------------------------------------------------------------

single_pulse/vhdl/single_pulse_tb.vcd
$date
  Sat Mar 21 18:38:01 2020
$end
$version
  GHDL v0
$end
$timescale
  1 fs
$end
$scope module standard $end
$upscope $end
$scope module std_logic_1164 $end
$upscope $end
$scope module numeric_std $end
$upscope $end
$scope module single_pulse_tb $end
$var reg 1 ! t_clk $end
$var reg 1 " t_rst_l $end
$var reg 1 # t_ub $end
$var reg 1 $ t_ubsing $end
$var reg 1 % stop_simulation $end
$scope module u_single_pulse $end
$var reg 1 & clk $end
$var reg 1 ' rst_l $end
$var reg 1 ( ub $end
$var reg 1 ) ubsing $end
$var reg 1 * next_state $end
$var reg 1 + state $end
$var reg 1 , ubsing_reg $end
$var reg 1 - next_ubsing_reg $end
$upscope $end
$upscope $end
$enddefinitions $end
#0
1!
0"
0#
0$
0%
1&
0'
0(
0)
0*
0+
0,
0-
#5000000
0!
0&
#10000000
1!
1&
#15000000
0!
0&
#20000000
1!
1"
1&
1'
#25000000
0!
0&
#30000000
1!
1&
#35000000
0!
0&
#40000000
1!
1&
#45000000
0!
0&
#50000000
1!
1#
1&
1(
1*
1-
#55000000
0!
0&
#60000000
1!
1$
1&
1)
1+
1,
0-
#65000000
0!
0&
#70000000
1!
0$
1&
0)
0,
#75000000
0!
0&
#80000000
1!
1&
#85000000
0!
0&
#90000000
1!
1&
#95000000
0!
0&
#100000000
1!
0#
1&
0(
0*
#105000000
0!
0&
#110000000
1!
1&
0+
#115000000
0!
0&
#120000000
1!
1&
#125000000
0!
0&
#130000000
1!
1&
#135000000
0!
0&
#140000000
1!
1&
#145000000
0!
0&
#150000000
1!
1%
1&
